ynm3k/__init__.py
ynm3k/echo.py
ynm3k/handlers.py
ynm3k/interact.py
ynm3k/mock.py
ynm3k/qiniu_serve.py
ynm3k/static.py
ynm3k/status_codes.py
ynm3k/util.py
ynm3k/weixin.py
ynm3k/ynm3k.py
ynm3k/contrib/__init__.py
ynm3k/contrib/bottle.py
ynm3k/modules/__init__.py
ynm3k/modules/zip_serve.py
ynm3k-0.4.8.data/scripts/y3k
ynm3k-0.4.8.dist-info/DESCRIPTION.rst
ynm3k-0.4.8.dist-info/METADATA
ynm3k-0.4.8.dist-info/RECORD
ynm3k-0.4.8.dist-info/WHEEL
ynm3k-0.4.8.dist-info/metadata.json
ynm3k-0.4.8.dist-info/top_level.txt
