Metadata-Version: 2.0
Name: ynm3k
Version: 0.4.8
Summary: UNKNOWN
Home-page: https://github.com/socrateslee/ynm3k
Author: Lichun
License: UNKNOWN
Platform: UNKNOWN
Classifier: Environment :: Console
Classifier: Intended Audience :: Developers
Classifier: License :: OSI Approved :: MIT License
Classifier: Programming Language :: Python
Provides-Extra: full
Requires-Dist: six
Requires-Dist: requests
Requires-Dist: hjson
Provides-Extra: full
Requires-Dist: bs4; extra == 'full'
Requires-Dist: paste; extra == 'full'
